fixedpackage1234567/__init__.py
fixedpackage1234567-1.0.0.dist-info/METADATA
fixedpackage1234567-1.0.0.dist-info/WHEEL
fixedpackage1234567-1.0.0.dist-info/top_level.txt
fixedpackage1234567-1.0.0.dist-info/RECORD
