Metadata-Version: 2.4
Name: fixedpackage1234567
Version: 1.0.0
Summary: Fixed python package
Author: Isabella Abbate
Author-email: isabellaabbate11@gmail.com
Classifier: Programming Language :: Python :: 3
Classifier: License :: OSI Approved :: MIT License
Classifier: Operating System :: OS Independent
